{"config":{"output_file":null,"full_docs":false,"pub_only":false,"reachable_only":false,"distro_crate":false,"signatures":false,"borrow_data":false},"version":"0.19.1","compilation":{"directory":"c:\\Users\\ds_wa\\OneDrive\\Documents\\Rust\\Learning-Rust\\challenge_roster","program":"C:\\Users\\ds_wa\\.rustup\\toolchains\\stable-x86_64-pc-windows-msvc\\bin\\rls.exe","arguments":[],"output":"c:\\Users\\ds_wa\\OneDrive\\Documents\\Rust\\Learning-Rust\\challenge_roster\\target\\rls\\debug\\deps\\libchallenge_roster-a5585414556bc8b2.rmeta"},"prelude":{"crate_id":{"name":"challenge_roster","disambiguator":[16088034382549263986,15285523136151035232]},"crate_root":"src","external_crates":[{"file_name":"c:\\Users\\ds_wa\\OneDrive\\Documents\\Rust\\Learning-Rust\\challenge_roster\\src\\main.rs","num":1,"id":{"name":"std","disambiguator":[3270634090130538391,14263718429753122316]}},{"file_name":"c:\\Users\\ds_wa\\OneDrive\\Documents\\Rust\\Learning-Rust\\challenge_roster\\src\\main.rs","num":2,"id":{"name":"core","disambiguator":[5532051063976025760,2256364509988431667]}},{"file_name":"c:\\Users\\ds_wa\\OneDrive\\Documents\\Rust\\Learning-Rust\\challenge_roster\\src\\main.rs","num":3,"id":{"name":"compiler_builtins","disambiguator":[7281929168992546274,2424678954744988439]}},{"file_name":"c:\\Users\\ds_wa\\OneDrive\\Documents\\Rust\\Learning-Rust\\challenge_roster\\src\\main.rs","num":4,"id":{"name":"rustc_std_workspace_core","disambiguator":[353429176083156877,8877241423562725442]}},{"file_name":"c:\\Users\\ds_wa\\OneDrive\\Documents\\Rust\\Learning-Rust\\challenge_roster\\src\\main.rs","num":5,"id":{"name":"alloc","disambiguator":[12196241746694410349,3365331946273478086]}},{"file_name":"c:\\Users\\ds_wa\\OneDrive\\Documents\\Rust\\Learning-Rust\\challenge_roster\\src\\main.rs","num":6,"id":{"name":"libc","disambiguator":[13433537899495627439,16859208643582984883]}},{"file_name":"c:\\Users\\ds_wa\\OneDrive\\Documents\\Rust\\Learning-Rust\\challenge_roster\\src\\main.rs","num":7,"id":{"name":"unwind","disambiguator":[8262757423788146228,17823423584984973278]}},{"file_name":"c:\\Users\\ds_wa\\OneDrive\\Documents\\Rust\\Learning-Rust\\challenge_roster\\src\\main.rs","num":8,"id":{"name":"cfg_if","disambiguator":[15770910386717746279,2673050061768012116]}},{"file_name":"c:\\Users\\ds_wa\\OneDrive\\Documents\\Rust\\Learning-Rust\\challenge_roster\\src\\main.rs","num":9,"id":{"name":"hashbrown","disambiguator":[15973938195753786773,1947565178479551552]}},{"file_name":"c:\\Users\\ds_wa\\OneDrive\\Documents\\Rust\\Learning-Rust\\challenge_roster\\src\\main.rs","num":10,"id":{"name":"rustc_std_workspace_alloc","disambiguator":[1495831041033125177,733230368880816191]}},{"file_name":"c:\\Users\\ds_wa\\OneDrive\\Documents\\Rust\\Learning-Rust\\challenge_roster\\src\\main.rs","num":11,"id":{"name":"rustc_demangle","disambiguator":[17679945988426249108,16004284943229030185]}},{"file_name":"c:\\Users\\ds_wa\\OneDrive\\Documents\\Rust\\Learning-Rust\\challenge_roster\\src\\main.rs","num":12,"id":{"name":"std_detect","disambiguator":[4674106540844190265,14311593861468432536]}},{"file_name":"c:\\Users\\ds_wa\\OneDrive\\Documents\\Rust\\Learning-Rust\\challenge_roster\\src\\main.rs","num":13,"id":{"name":"panic_unwind","disambiguator":[12112277384381649788,786361786206656603]}},{"file_name":"c:\\Users\\ds_wa\\OneDrive\\Documents\\Rust\\Learning-Rust\\challenge_roster\\src\\main.rs","num":14,"id":{"name":"test","disambiguator":[15155498655906665088,13039784506209073555]}},{"file_name":"c:\\Users\\ds_wa\\OneDrive\\Documents\\Rust\\Learning-Rust\\challenge_roster\\src\\main.rs","num":15,"id":{"name":"getopts","disambiguator":[3094041984913192215,14591063090523489554]}},{"file_name":"c:\\Users\\ds_wa\\OneDrive\\Documents\\Rust\\Learning-Rust\\challenge_roster\\src\\main.rs","num":16,"id":{"name":"rustc_std_workspace_std","disambiguator":[9122446236157720767,9592091509327829974]}},{"file_name":"c:\\Users\\ds_wa\\OneDrive\\Documents\\Rust\\Learning-Rust\\challenge_roster\\src\\main.rs","num":17,"id":{"name":"unicode_width","disambiguator":[16839276830846757512,6576631722041160478]}},{"file_name":"c:\\Users\\ds_wa\\OneDrive\\Documents\\Rust\\Learning-Rust\\challenge_roster\\src\\main.rs","num":18,"id":{"name":"term","disambiguator":[2709571172283088031,18216411021382534889]}}],"span":{"file_name":"src\\main.rs","byte_start":0,"byte_end":524,"line_start":1,"line_end":24,"column_start":1,"column_end":2}},"imports":[{"kind":"Use","ref_id":{"krate":1,"index":2958},"span":{"file_name":"src\\main.rs","byte_start":9,"byte_end":11,"line_start":1,"line_end":1,"column_start":10,"column_end":12},"alias_span":null,"name":"fs","value":"","parent":{"krate":0,"index":0}},{"kind":"Use","ref_id":{"krate":1,"index":2131},"span":{"file_name":"src\\main.rs","byte_start":22,"byte_end":25,"line_start":2,"line_end":2,"column_start":10,"column_end":13},"alias_span":null,"name":"env","value":"","parent":{"krate":0,"index":0}},{"kind":"Use","ref_id":{"krate":2,"index":20},"span":{"file_name":"src\\main.rs","byte_start":22,"byte_end":25,"line_start":2,"line_end":2,"column_start":10,"column_end":13},"alias_span":null,"name":"env","value":"","parent":{"krate":0,"index":0}}],"defs":[{"kind":"Mod","id":{"krate":0,"index":0},"span":{"file_name":"src\\main.rs","byte_start":0,"byte_end":524,"line_start":1,"line_end":24,"column_start":1,"column_end":2},"name":"","qualname":"::","value":"src\\main.rs","parent":null,"children":[{"krate":0,"index":1},{"krate":0,"index":2},{"krate":0,"index":3},{"krate":0,"index":6},{"krate":0,"index":7},{"krate":0,"index":9},{"krate":0,"index":10}],"decl_id":null,"docs":"","sig":null,"attributes":[]},{"kind":"Function","id":{"krate":0,"index":9},"span":{"file_name":"src\\main.rs","byte_start":31,"byte_end":35,"line_start":4,"line_end":4,"column_start":4,"column_end":8},"name":"main","qualname":"::main","value":"fn main()","parent":null,"children":[],"decl_id":null,"docs":"","sig":null,"attributes":[{"value":"allow(dead_code)","span":{"file_name":"src\\main.rs","byte_start":0,"byte_end":0,"line_start":1,"line_end":1,"column_start":1,"column_end":1}}]},{"kind":"Local","id":{"krate":0,"index":3422552073},"span":{"file_name":"src\\main.rs","byte_start":165,"byte_end":174,"line_start":10,"line_end":10,"column_start":9,"column_end":18},"name":"file_path","qualname":"file_path$HirId { owner: DefId(0:9 ~ challenge_roster[df44]::main), local_id: 51 }","value":"std::string::String","parent":null,"children":[],"decl_id":null,"docs":"","sig":null,"attributes":[]},{"kind":"Local","id":{"krate":0,"index":4227858441},"span":{"file_name":"src\\main.rs","byte_start":214,"byte_end":218,"line_start":11,"line_end":11,"column_start":9,"column_end":13},"name":"name","qualname":"name$HirId { owner: DefId(0:9 ~ challenge_roster[df44]::main), local_id: 63 }","value":"std::string::String","parent":null,"children":[],"decl_id":null,"docs":"","sig":null,"attributes":[]},{"kind":"Local","id":{"krate":0,"index":1375731721},"span":{"file_name":"src\\main.rs","byte_start":263,"byte_end":271,"line_start":13,"line_end":13,"column_start":9,"column_end":17},"name":"contents","qualname":"contents$HirId { owner: DefId(0:9 ~ challenge_roster[df44]::main), local_id: 74 }","value":"std::string::String","parent":null,"children":[],"decl_id":null,"docs":"","sig":null,"attributes":[]},{"kind":"Local","id":{"krate":0,"index":973078537},"span":{"file_name":"src\\main.rs","byte_start":331,"byte_end":347,"line_start":15,"line_end":15,"column_start":17,"column_end":33},"name":"iter","qualname":"iter$HirId { owner: DefId(0:9 ~ challenge_roster[df44]::main), local_id: 92 }","value":"std::str::Lines","parent":null,"children":[],"decl_id":null,"docs":"","sig":null,"attributes":[]},{"kind":"Local","id":{"krate":0,"index":167772169},"span":{"file_name":"src\\main.rs","byte_start":331,"byte_end":347,"line_start":15,"line_end":15,"column_start":17,"column_end":33},"name":"__next","qualname":"__next$HirId { owner: DefId(0:9 ~ challenge_roster[df44]::main), local_id: 80 }","value":"&str","parent":null,"children":[],"decl_id":null,"docs":"","sig":null,"attributes":[]},{"kind":"Local","id":{"krate":0,"index":2315255817},"span":{"file_name":"src\\main.rs","byte_start":323,"byte_end":327,"line_start":15,"line_end":15,"column_start":9,"column_end":13},"name":"val","qualname":"val$HirId { owner: DefId(0:9 ~ challenge_roster[df44]::main), local_id: 81 }","value":"&str","parent":null,"children":[],"decl_id":null,"docs":"","sig":null,"attributes":[]},{"kind":"Local","id":{"krate":0,"index":1711276041},"span":{"file_name":"src\\main.rs","byte_start":323,"byte_end":327,"line_start":15,"line_end":15,"column_start":9,"column_end":13},"name":"line","qualname":"line$HirId { owner: DefId(0:9 ~ challenge_roster[df44]::main), local_id: 102 }","value":"&str","parent":null,"children":[],"decl_id":null,"docs":"","sig":null,"attributes":[]}],"impls":[],"refs":[{"kind":"Mod","span":{"file_name":"src\\main.rs","byte_start":4,"byte_end":7,"line_start":1,"line_end":1,"column_start":5,"column_end":8},"ref_id":{"krate":1,"index":0}},{"kind":"Mod","span":{"file_name":"src\\main.rs","byte_start":17,"byte_end":20,"line_start":2,"line_end":2,"column_start":5,"column_end":8},"ref_id":{"krate":1,"index":0}},{"kind":"Function","span":{"file_name":"src\\main.rs","byte_start":59,"byte_end":62,"line_start":5,"line_end":5,"column_start":20,"column_end":23},"ref_id":{"krate":2,"index":7130}},{"kind":"Function","span":{"file_name":"src\\main.rs","byte_start":52,"byte_end":56,"line_start":5,"line_end":5,"column_start":13,"column_end":17},"ref_id":{"krate":1,"index":2230}},{"kind":"Mod","span":{"file_name":"src\\main.rs","byte_start":47,"byte_end":50,"line_start":5,"line_end":5,"column_start":8,"column_end":11},"ref_id":{"krate":1,"index":2131}},{"kind":"Function","span":{"file_name":"src\\main.rs","byte_start":196,"byte_end":202,"line_start":10,"line_end":10,"column_start":40,"column_end":46},"ref_id":{"krate":2,"index":7681}},{"kind":"Function","span":{"file_name":"src\\main.rs","byte_start":189,"byte_end":192,"line_start":10,"line_end":10,"column_start":33,"column_end":36},"ref_id":{"krate":2,"index":7250}},{"kind":"Function","span":{"file_name":"src\\main.rs","byte_start":182,"byte_end":186,"line_start":10,"line_end":10,"column_start":26,"column_end":30},"ref_id":{"krate":1,"index":2230}},{"kind":"Mod","span":{"file_name":"src\\main.rs","byte_start":177,"byte_end":180,"line_start":10,"line_end":10,"column_start":21,"column_end":24},"ref_id":{"krate":1,"index":2131}},{"kind":"Function","span":{"file_name":"src\\main.rs","byte_start":240,"byte_end":246,"line_start":11,"line_end":11,"column_start":35,"column_end":41},"ref_id":{"krate":2,"index":7681}},{"kind":"Function","span":{"file_name":"src\\main.rs","byte_start":233,"byte_end":236,"line_start":11,"line_end":11,"column_start":28,"column_end":31},"ref_id":{"krate":2,"index":7250}},{"kind":"Function","span":{"file_name":"src\\main.rs","byte_start":226,"byte_end":230,"line_start":11,"line_end":11,"column_start":21,"column_end":25},"ref_id":{"krate":1,"index":2230}},{"kind":"Mod","span":{"file_name":"src\\main.rs","byte_start":221,"byte_end":224,"line_start":11,"line_end":11,"column_start":16,"column_end":19},"ref_id":{"krate":1,"index":2131}},{"kind":"Function","span":{"file_name":"src\\main.rs","byte_start":304,"byte_end":310,"line_start":13,"line_end":13,"column_start":50,"column_end":56},"ref_id":{"krate":2,"index":8168}},{"kind":"Function","span":{"file_name":"src\\main.rs","byte_start":278,"byte_end":292,"line_start":13,"line_end":13,"column_start":24,"column_end":38},"ref_id":{"krate":1,"index":3026}},{"kind":"Mod","span":{"file_name":"src\\main.rs","byte_start":274,"byte_end":276,"line_start":13,"line_end":13,"column_start":20,"column_end":22},"ref_id":{"krate":1,"index":2958}},{"kind":"Variable","span":{"file_name":"src\\main.rs","byte_start":293,"byte_end":302,"line_start":13,"line_end":13,"column_start":39,"column_end":48},"ref_id":{"krate":0,"index":3422552073}},{"kind":"Variable","span":{"file_name":"src\\main.rs","byte_start":331,"byte_end":339,"line_start":15,"line_end":15,"column_start":17,"column_end":25},"ref_id":{"krate":0,"index":1375731721}},{"kind":"Variable","span":{"file_name":"src\\main.rs","byte_start":323,"byte_end":327,"line_start":15,"line_end":15,"column_start":9,"column_end":13},"ref_id":{"krate":2,"index":39713}},{"kind":"Variable","span":{"file_name":"src\\main.rs","byte_start":361,"byte_end":365,"line_start":16,"line_end":16,"column_start":12,"column_end":16},"ref_id":{"krate":0,"index":1711276041}},{"kind":"Variable","span":{"file_name":"src\\main.rs","byte_start":369,"byte_end":373,"line_start":16,"line_end":16,"column_start":20,"column_end":24},"ref_id":{"krate":0,"index":4227858441}}],"macro_refs":[],"relations":[]}